LICENSE.txt
MANIFEST.in
README.rst
pavement.py
requirements-dev.txt
requirements.txt
setup.py
tox.ini
docs/Makefile
docs/make.bat
docs/source/README
docs/source/conf.py
docs/source/index.rst
docs/source/_static/.gitkeep
pybitbucket/__init__.py
pybitbucket/auth.py
pybitbucket/bitbucket.py
pybitbucket/branchrestriction.py
pybitbucket/build.py
pybitbucket/comment.py
pybitbucket/commit.py
pybitbucket/consumer.py
pybitbucket/entrypoints.py
pybitbucket/hook.py
pybitbucket/main.py
pybitbucket/metadata.py
pybitbucket/pullrequest.py
pybitbucket/ref.py
pybitbucket/repository.py
pybitbucket/snippet.py
pybitbucket/team.py
pybitbucket/user.py
pybitbucket.egg-info/PKG-INFO
pybitbucket.egg-info/SOURCES.txt
pybitbucket.egg-info/dependency_links.txt
pybitbucket.egg-info/entry_points.txt
pybitbucket.egg-info/not-zip-safe
pybitbucket.egg-info/requires.txt
pybitbucket.egg-info/top_level.txt
tests/Branch.json
tests/BranchRestriction.json
tests/BranchRestrictionPayload.full.json
tests/BranchRestrictionPayload.minimal.json
tests/BranchRestriction_list.json
tests/Branch_list.json
tests/BuildStatus.json
tests/BuildStatusPayload.full.json
tests/BuildStatusPayload.json
tests/BuildStatusPayload.minimal.json
tests/Comment.json
tests/Comment_list.json
tests/Commit.json
tests/Commit_list.json
tests/Consumer.json
tests/ConsumerPayload.full.json
tests/ConsumerPayload.minimal.json
tests/Consumer_list.json
tests/Diff.txt
tests/Hook.json
tests/HookPayload.full.json
tests/HookPayload.minimal.json
tests/Hook_list.json
tests/Issue.json
tests/Issue_list.json
tests/PullRequest.activity.json
tests/PullRequest.approve.json
tests/PullRequest.decline.json
tests/PullRequest.json
tests/PullRequest.merge.json
tests/PullRequestPayload.full.json
tests/PullRequestPayload.minimal.json
tests/PullRequest_list.json
tests/Ref_list.json
tests/Repository.json
tests/RepositoryPayload.full.json
tests/RepositoryPayload.json
tests/RepositoryPayload.minimal.json
tests/RepositoryV1.json
tests/RepositoryV1_list.json
tests/Repository_create.json
tests/Repository_list.json
tests/Snippet.json
tests/Snippet.two_files.json
tests/SnippetPayload.full.json
tests/Snippet_list.json
tests/Tag.json
tests/Tag_list.json
tests/User.json
tests/UserV1.json
tests/User_list.json
